[
  {
    "seed": 1775148627958,
    "room_index": 21,
    "biome_index": 3,
    "player_state": "STRUGGLING",
    "difficulty_modifier": 0.85,
    "enemy_adjustment": -1,
    "reinforcement_chance": 0.0,
    "room_result": "damaged_clear",
    "hp_end": 28.740999999999996,
    "damage_taken": 142.51800000000003,
    "hp_percent_start_room": 100.0,
    "min_hp_during_room": 28.740999999999996,
    "max_hp_during_room": 100.0,
    "hp_lost_in_room": 71.259
  },
  {
    "seed": 1775148627958,
    "room_index": 21,
    "biome_index": 3,
    "player_state": "STRUGGLING",
    "difficulty_modifier": 0.85,
    "enemy_adjustment": -1,
    "reinforcement_chance": 0.0,
    "room_result": "damaged_clear",
    "hp_end": 28.740999999999996,
    "damage_taken": 142.51800000000003,
    "hp_percent_start_room": 100.0,
    "min_hp_during_room": 28.740999999999996,
    "max_hp_during_room": 100.0,
    "hp_lost_in_room": 71.259
  },
  {
    "seed": 1775148627958,
    "room_index": 22,
    "biome_index": 3,
    "player_state": "STRUGGLING",
    "difficulty_modifier": 0.85,
    "enemy_adjustment": -1,
    "reinforcement_chance": 0.0,
    "room_result": "clean_clear",
    "hp_end": 15.740999999999996,
    "damage_taken": 26.0,
    "hp_percent_start_room": 28.740999999999996,
    "min_hp_during_room": 15.740999999999996,
    "max_hp_during_room": 28.740999999999996,
    "hp_lost_in_room": 13.0
  },
  {
    "seed": 1775148627958,
    "room_index": 22,
    "biome_index": 3,
    "player_state": "STRUGGLING",
    "difficulty_modifier": 0.85,
    "enemy_adjustment": -1,
    "reinforcement_chance": 0.0,
    "room_result": "clean_clear",
    "hp_end": 15.740999999999996,
    "damage_taken": 26.0,
    "hp_percent_start_room": 28.740999999999996,
    "min_hp_during_room": 15.740999999999996,
    "max_hp_during_room": 28.740999999999996,
    "hp_lost_in_room": 13.0
  },
  {
    "seed": 1775148627958,
    "room_index": 23,
    "biome_index": 3,
    "player_state": "STRUGGLING",
    "difficulty_modifier": 0.85,
    "enemy_adjustment": -1,
    "reinforcement_chance": 0.0,
    "room_result": "near_death",
    "hp_end": 56.0,
    "damage_taken": 78.0,
    "hp_percent_start_room": 15.740999999999996,
    "min_hp_during_room": 0.0,
    "max_hp_during_room": 100.0,
    "hp_lost_in_room": 15.740999999999996
  },
  {
    "seed": 1775148627958,
    "room_index": 23,
    "biome_index": 3,
    "player_state": "STABLE",
    "difficulty_modifier": 1.0,
    "enemy_adjustment": 0,
    "reinforcement_chance": 0.1,
    "room_result": "near_death",
    "hp_end": 56.0,
    "damage_taken": 78.0,
    "hp_percent_start_room": 15.740999999999996,
    "min_hp_during_room": 0.0,
    "max_hp_during_room": 100.0,
    "hp_lost_in_room": 15.740999999999996
  },
  {
    "seed": 1775148627958,
    "room_index": 24,
    "biome_index": 4,
    "player_state": "STRUGGLING",
    "difficulty_modifier": 0.85,
    "enemy_adjustment": -1,
    "reinforcement_chance": 0.0,
    "room_result": "damaged_clear",
    "hp_end": 48.0,
    "damage_taken": 38.0,
    "hp_percent_start_room": 86.0,
    "min_hp_during_room": 48.0,
    "max_hp_during_room": 86.0,
    "hp_lost_in_room": 38.0
  },
  {
    "seed": 1775148627958,
    "room_index": 24,
    "biome_index": 4,
    "player_state": "STABLE",
    "difficulty_modifier": 1.0,
    "enemy_adjustment": 0,
    "reinforcement_chance": 0.1,
    "room_result": "damaged_clear",
    "hp_end": 48.0,
    "damage_taken": 38.0,
    "hp_percent_start_room": 86.0,
    "min_hp_during_room": 48.0,
    "max_hp_during_room": 86.0,
    "hp_lost_in_room": 38.0
  },
  {
    "seed": 1775148627958,
    "room_index": 25,
    "biome_index": 4,
    "player_state": "STRUGGLING",
    "difficulty_modifier": 0.85,
    "enemy_adjustment": -1,
    "reinforcement_chance": 0.0,
    "room_result": "near_death",
    "hp_end": 5.693999999999983,
    "damage_taken": 72.30599999999984,
    "hp_percent_start_room": 78.0,
    "min_hp_during_room": 5.693999999999983,
    "max_hp_during_room": 78.0,
    "hp_lost_in_room": 72.30600000000001
  },
  {
    "seed": 1775148627958,
    "room_index": 25,
    "biome_index": 4,
    "player_state": "STRUGGLING",
    "difficulty_modifier": 0.85,
    "enemy_adjustment": -1,
    "reinforcement_chance": 0.0,
    "room_result": "near_death",
    "hp_end": 5.693999999999983,
    "damage_taken": 72.30599999999984,
    "hp_percent_start_room": 78.0,
    "min_hp_during_room": 5.693999999999983,
    "max_hp_during_room": 78.0,
    "hp_lost_in_room": 72.30600000000001
  },
  {
    "seed": 1775148627958,
    "room_index": 26,
    "biome_index": 4,
    "player_state": "STRUGGLING",
    "difficulty_modifier": 0.85,
    "enemy_adjustment": -1,
    "reinforcement_chance": 0.0,
    "room_result": "near_death",
    "hp_end": 100.0,
    "damage_taken": 12.0,
    "hp_percent_start_room": 5.693999999999983,
    "min_hp_during_room": 0.0,
    "max_hp_during_room": 100.0,
    "hp_lost_in_room": 5.693999999999983
  },
  {
    "seed": 1775148627958,
    "room_index": 26,
    "biome_index": 4,
    "player_state": "STRUGGLING",
    "difficulty_modifier": 0.85,
    "enemy_adjustment": -1,
    "reinforcement_chance": 0.0,
    "room_result": "near_death",
    "hp_end": 100.0,
    "damage_taken": 12.0,
    "hp_percent_start_room": 5.693999999999983,
    "min_hp_during_room": 0.0,
    "max_hp_during_room": 100.0,
    "hp_lost_in_room": 5.693999999999983
  },
  {
    "seed": 1775148627958,
    "room_index": 27,
    "biome_index": 4,
    "player_state": "STRUGGLING",
    "difficulty_modifier": 0.85,
    "enemy_adjustment": -1,
    "reinforcement_chance": 0.0,
    "room_result": "clean_clear",
    "hp_end": 100.0,
    "damage_taken": 0.0,
    "hp_percent_start_room": 100.0,
    "min_hp_during_room": 100.0,
    "max_hp_during_room": 100.0,
    "hp_lost_in_room": 0.0
  },
  {
    "seed": 1775148627958,
    "room_index": 28,
    "biome_index": 4,
    "player_state": "STRUGGLING",
    "difficulty_modifier": 0.85,
    "enemy_adjustment": -1,
    "reinforcement_chance": 0.0,
    "room_result": "clean_clear",
    "hp_end": 84.0,
    "damage_taken": 8.0,
    "hp_percent_start_room": 100.0,
    "min_hp_during_room": 84.0,
    "max_hp_during_room": 100.0,
    "hp_lost_in_room": 16.0
  },
  {
    "seed": 1775148627958,
    "room_index": 28,
    "biome_index": 4,
    "player_state": "STRUGGLING",
    "difficulty_modifier": 0.85,
    "enemy_adjustment": -1,
    "reinforcement_chance": 0.0,
    "room_result": "clean_clear",
    "hp_end": 84.0,
    "damage_taken": 8.0,
    "hp_percent_start_room": 100.0,
    "min_hp_during_room": 84.0,
    "max_hp_during_room": 100.0,
    "hp_lost_in_room": 16.0
  }
]